ewlibs/__init__.py
ewlibs/char_handler.py
ewlibs/jsonp_handler.py
ewlibs/nlp_handler.py
ewlibs/path_handler.py
ewlibs/re_handler.py
ewlibs/requests_handler.py
ewlibs/testcode.py
ewlibs/file/__init__.py
ewlibs/file/paging.py
ewlibs/mongo/__init__.py
ewlibs/mongo/conn_mongo.py
ewlibs-0.0.28.dist-info/METADATA
ewlibs-0.0.28.dist-info/WHEEL
ewlibs-0.0.28.dist-info/top_level.txt
ewlibs-0.0.28.dist-info/RECORD
